mondemand/__init__.py
mondemand/_mondemand.so
mondemand/client.py
mondemand/lwes_transport.py
mondemand/py.typed
mondemand/utils.py
mondemand-1.0.1.dist-info/METADATA
mondemand-1.0.1.dist-info/RECORD
mondemand-1.0.1.dist-info/WHEEL
mondemand-1.0.1.dist-info/top_level.txt
