Metadata-Version: 2.1
Name: mondemand
Version: 1.0.1
Summary: MonDemand python bindings
Home-page: https://github.com/mondemand/mondemand-python
Maintainer: Derek Kulinski
Maintainer-email: d@kulinski.us
License: BSD
Platform: POSIX
Classifier: Development Status :: 4 - Beta
Classifier: Intended Audience :: Developers
Classifier: License :: OSI Approved :: BSD License
Classifier: Operating System :: Unix
Classifier: Programming Language :: Python
Classifier: Programming Language :: Python :: 2
Classifier: Programming Language :: Python :: 2.7
Classifier: Programming Language :: Python :: 3
Classifier: Programming Language :: Python :: 3.4
Classifier: Programming Language :: Python :: 3.5
Classifier: Programming Language :: Python :: 3.6
Classifier: Programming Language :: Python :: 3.7
Classifier: Topic :: Software Development :: Libraries :: Python Modules
Requires-Python: 
Requires-Dist: cffi (~=1.11.5)
Requires-Dist: six
Requires-Dist: typing
